trovotutto/__init__.py
trovotutto/color.py
trovotutto-0.0.1.1.dist-info/LICENSE
trovotutto-0.0.1.1.dist-info/METADATA
trovotutto-0.0.1.1.dist-info/WHEEL
trovotutto-0.0.1.1.dist-info/entry_points.txt
trovotutto-0.0.1.1.dist-info/top_level.txt
trovotutto-0.0.1.1.dist-info/RECORD
