Metadata-Version: 2.1
Name: trovotutto
Version: 0.0.1.1
Summary: small search engine using k-grams
Home-page: https://github.com/tallero/trovotutto
Author: Pellegrino Prevete
Author-email: pellegrinoprevete@gmail.com
License: UNKNOWN
Platform: UNKNOWN
Classifier: Programming Language :: Python :: 3
Classifier: License :: OSI Approved :: GNU General Public License v3 or later (GPLv3+)
Classifier: Operating System :: Unix
Requires-Dist: nltk
Requires-Dist: pyxdg
